monet_pytorch/__init__.py
monet_pytorch/attention_net.py
monet_pytorch/config/dataset/clevr_6.yaml
monet_pytorch/config/dataset/multidsprites_colored_on_colored.yaml
monet_pytorch/config/dataset/multidsprites_colored_on_grayscale.yaml
monet_pytorch/config/dataset/tetrominoes.yaml
monet_pytorch/config/model/monet-iodine.yaml
monet_pytorch/config/model/monet-lightweight.yaml
monet_pytorch/config/model/monet.yaml
monet_pytorch/config/special_cases/monet-clevr_6.yaml
monet_pytorch/config/special_cases/monet-iodine-clevr_6.yaml
monet_pytorch/config/special_cases/monet-iodine-tetrominoes.yaml
monet_pytorch/config/special_cases/monet-lightweight-clevr_6.yaml
monet_pytorch/config/special_cases/monet-lightweight-multidsprites_colored_on_grayscale.yaml
monet_pytorch/config/special_cases/monet-lightweight-tetrominoes.yaml
monet_pytorch/config/special_cases/monet-tetrominoes.yaml
monet_pytorch/init_config.py
monet_pytorch/model.py
monet_pytorch/nn_utils.py
monet_pytorch/paths.py
monet_pytorch/template/__init__.py
monet_pytorch/template/encoder_decoder.py
monet_pytorch/template/sequential_cnn.py
monet_pytorch/unet.py
monet_pytorch-1.1.0.dist-info/LICENSE
monet_pytorch-1.1.0.dist-info/WHEEL
monet_pytorch-1.1.0.dist-info/METADATA
monet_pytorch-1.1.0.dist-info/RECORD
